{
  "schema_version": 1,
  "id": "global_flows",
  "title": "Global flows & allocation",
  "description": "Cross-border trade flows, asset-class allocation, counterparty network, mandate conversion funnel.",
  "theme": "gs_clean",
  "palette": "gs_primary",
  "datasets": {
    "flows": {
      "source": [
        [
          "src",
          "tgt",
          "v"
        ],
        [
          "United States \u2192",
          "\u2190 China",
          650
        ],
        [
          "United States \u2192",
          "\u2190 Mexico",
          830
        ],
        [
          "United States \u2192",
          "\u2190 Canada",
          720
        ],
        [
          "United States \u2192",
          "\u2190 EU",
          590
        ],
        [
          "United States \u2192",
          "\u2190 Japan",
          230
        ],
        [
          "United States \u2192",
          "\u2190 UK",
          145
        ],
        [
          "China \u2192",
          "\u2190 United States",
          540
        ],
        [
          "China \u2192",
          "\u2190 EU",
          700
        ],
        [
          "China \u2192",
          "\u2190 Japan",
          280
        ],
        [
          "China \u2192",
          "\u2190 Brazil",
          170
        ],
        [
          "EU \u2192",
          "\u2190 United States",
          610
        ],
        [
          "EU \u2192",
          "\u2190 China",
          290
        ],
        [
          "EU \u2192",
          "\u2190 UK",
          480
        ],
        [
          "Japan \u2192",
          "\u2190 United States",
          160
        ],
        [
          "Japan \u2192",
          "\u2190 China",
          195
        ]
      ]
    },
    "share": {
      "source": [
        [
          "region",
          "outbound"
        ],
        [
          "China",
          1690
        ],
        [
          "EU",
          1380
        ],
        [
          "Japan",
          355
        ],
        [
          "United States",
          3165
        ]
      ]
    },
    "tree": {
      "source": [
        [
          "region",
          "country",
          "asset_class",
          "aum"
        ],
        [
          "North America",
          "United States",
          "Equities",
          4200
        ],
        [
          "North America",
          "United States",
          "Rates",
          3100
        ],
        [
          "North America",
          "United States",
          "Credit",
          1400
        ],
        [
          "North America",
          "Canada",
          "Rates",
          250
        ],
        [
          "North America",
          "Canada",
          "Equities",
          310
        ],
        [
          "Europe",
          "UK",
          "Rates",
          520
        ],
        [
          "Europe",
          "UK",
          "Equities",
          410
        ],
        [
          "Europe",
          "Germany",
          "Rates",
          610
        ],
        [
          "Europe",
          "Germany",
          "Equities",
          320
        ],
        [
          "Europe",
          "France",
          "Rates",
          390
        ],
        [
          "Europe",
          "France",
          "Credit",
          220
        ],
        [
          "APAC",
          "Japan",
          "Rates",
          780
        ],
        [
          "APAC",
          "Japan",
          "Equities",
          420
        ],
        [
          "APAC",
          "China",
          "Equities",
          610
        ],
        [
          "APAC",
          "China",
          "Rates",
          380
        ],
        [
          "APAC",
          "India",
          "Equities",
          290
        ],
        [
          "EM",
          "Brazil",
          "Commodities",
          210
        ],
        [
          "EM",
          "Mexico",
          "Credit",
          180
        ],
        [
          "EM",
          "Mexico",
          "Equities",
          140
        ]
      ]
    },
    "funnel": {
      "source": [
        [
          "stage",
          "aum_bn"
        ],
        [
          "Prospects reached",
          1200
        ],
        [
          "First meeting",
          740
        ],
        [
          "Mandate discussion",
          430
        ],
        [
          "Proposal sent",
          260
        ],
        [
          "Signed",
          145
        ],
        [
          "Funded",
          128
        ]
      ]
    },
    "net": {
      "source": [
        [
          "src",
          "tgt",
          "v",
          "category"
        ],
        [
          "GS",
          "JPM",
          35,
          "Bank"
        ],
        [
          "GS",
          "MS",
          28,
          "Bank"
        ],
        [
          "GS",
          "BLK",
          42,
          "Bank"
        ],
        [
          "GS",
          "BAC",
          20,
          "Bank"
        ],
        [
          "JPM",
          "MS",
          15,
          "Bank"
        ],
        [
          "JPM",
          "BLK",
          25,
          "Bank"
        ],
        [
          "JPM",
          "Vanguard",
          30,
          "Bank"
        ],
        [
          "MS",
          "BLK",
          18,
          "Bank"
        ],
        [
          "MS",
          "Vanguard",
          22,
          "Bank"
        ],
        [
          "BAC",
          "BLK",
          16,
          "Bank"
        ],
        [
          "BAC",
          "Vanguard",
          12,
          "Bank"
        ],
        [
          "BLK",
          "CalPERS",
          28,
          "AM"
        ],
        [
          "BLK",
          "GPFG",
          34,
          "AM"
        ],
        [
          "Vanguard",
          "CalPERS",
          19,
          "AM"
        ],
        [
          "Vanguard",
          "GPFG",
          22,
          "AM"
        ],
        [
          "CalPERS",
          "CalPERS",
          0,
          "Pension"
        ],
        [
          "GPFG",
          "GPFG",
          0,
          "Pension"
        ]
      ]
    }
  },
  "layout": {
    "kind": "tabs",
    "tabs": [
      {
        "id": "flows",
        "label": "Flows",
        "description": "Bilateral trade flows (sankey) and outbound share (donut).",
        "rows": [
          [
            {
              "widget": "stat_grid",
              "id": "flow_summary",
              "w": 12,
              "title": "Flow headlines (USD bn)",
              "stats": [
                {
                  "id": "s1",
                  "label": "Total flows",
                  "value": "6590",
                  "sub": "USD bn, all pairs"
                },
                {
                  "id": "s2",
                  "label": "Largest bilateral",
                  "value": "830",
                  "sub": "US \u2192 Mexico"
                },
                {
                  "id": "s3",
                  "label": "Bilateral legs",
                  "value": "15",
                  "sub": "directed pairs"
                },
                {
                  "id": "s4",
                  "label": "Top exporter",
                  "value": "US",
                  "sub": "USD 3,165 bn"
                },
                {
                  "id": "s5",
                  "label": "APAC share",
                  "value": "29%",
                  "sub": "of outbound"
                },
                {
                  "id": "s6",
                  "label": "YoY growth",
                  "value": "+4.2%",
                  "sub": "nominal, USD"
                }
              ]
            }
          ],
          [
            {
              "widget": "chart",
              "id": "flow_sankey",
              "w": 8,
              "h_px": 480,
              "spec": {
                "chart_type": "sankey",
                "dataset": "flows",
                "mapping": {
                  "source": "src",
                  "target": "tgt",
                  "value": "v"
                },
                "title": "Bilateral trade flows (USD bn)"
              }
            },
            {
              "widget": "chart",
              "id": "flow_donut",
              "w": 4,
              "h_px": 480,
              "spec": {
                "chart_type": "donut",
                "dataset": "share",
                "mapping": {
                  "category": "region",
                  "value": "outbound",
                  "legend_position": "bottom"
                },
                "title": "Outbound share"
              }
            }
          ]
        ]
      },
      {
        "id": "alloc",
        "label": "Allocation",
        "description": "AUM hierarchy across region \u2192 country \u2192 asset class.",
        "rows": [
          [
            {
              "widget": "chart",
              "id": "alloc_tree",
              "w": 6,
              "h_px": 480,
              "spec": {
                "chart_type": "treemap",
                "dataset": "tree",
                "mapping": {
                  "path": [
                    "region",
                    "country",
                    "asset_class"
                  ],
                  "value": "aum"
                },
                "title": "AUM treemap (USD bn)"
              }
            },
            {
              "widget": "chart",
              "id": "alloc_sun",
              "w": 6,
              "h_px": 480,
              "spec": {
                "chart_type": "sunburst",
                "dataset": "tree",
                "mapping": {
                  "path": [
                    "region",
                    "country",
                    "asset_class"
                  ],
                  "value": "aum"
                },
                "title": "AUM sunburst"
              }
            }
          ]
        ]
      },
      {
        "id": "network",
        "label": "Counterparty network",
        "description": "Bank-asset-manager-pension exposure graph.",
        "rows": [
          [
            {
              "widget": "chart",
              "id": "net_graph",
              "w": 12,
              "h_px": 520,
              "spec": {
                "chart_type": "graph",
                "dataset": "net",
                "mapping": {
                  "source": "src",
                  "target": "tgt",
                  "value": "v",
                  "node_category": "category"
                },
                "title": "Counterparty exposure network (drag nodes)"
              }
            }
          ]
        ]
      },
      {
        "id": "funnel",
        "label": "Mandate funnel",
        "description": "Prospect \u2192 funded conversion funnel.",
        "rows": [
          [
            {
              "widget": "chart",
              "id": "fun_chart",
              "w": 8,
              "h_px": 440,
              "spec": {
                "chart_type": "funnel",
                "dataset": "funnel",
                "mapping": {
                  "category": "stage",
                  "value": "aum_bn"
                },
                "title": "Prospect-to-funded pipeline (USD bn)"
              }
            },
            {
              "widget": "markdown",
              "id": "fun_notes",
              "w": 4,
              "content": "### Conversion commentary\n\nRoughly 10.7% of initial prospect AUM converts to funded mandates. The largest drop-off is between first meeting and mandate discussion (~42%).\n\nHistorical average funded rate is ~9.5%. Current cohort running slightly above."
            }
          ]
        ]
      }
    ]
  },
  "links": []
}